license_agent_client/__init__.py
license_agent_client/client.py
license_agent_client/config.py
license_agent_client/fastapi.py
license_agent_client/invokeapi.py
license_agent_client/middleware.py
license_agent_client/router.py
license_agent_client/ui.py
license_agent_client/ui/activate.html
license_agent_client/ui/license_gate.js
license_agent_client-1.0.1.dist-info/METADATA
license_agent_client-1.0.1.dist-info/WHEEL
license_agent_client-1.0.1.dist-info/licenses/LICENSE
license_agent_client-1.0.1.dist-info/RECORD
