Metadata-Version: 2.4
Name: license-agent-client
Version: 1.0.1
Summary: Dependency-free Python client for a local license-agent, with optional FastAPI enforcement helpers.
Project-URL: Homepage, https://example.invalid
Project-URL: Repository, https://example.invalid
Author: MeyiConnect
License: MIT License
License-File: LICENSE
Keywords: agent,fastapi,lease,license,licensing
Classifier: Development Status :: 3 - Alpha
Classifier: Intended Audience :: Developers
Classifier: License :: OSI Approved :: MIT License
Classifier: Programming Language :: Python :: 3
Classifier: Programming Language :: Python :: 3 :: Only
Classifier: Programming Language :: Python :: 3.9
Classifier: Programming Language :: Python :: 3.10
Classifier: Programming Language :: Python :: 3.11
Classifier: Programming Language :: Python :: 3.12
Classifier: Topic :: Software Development :: Libraries
Requires-Python: >=3.9
Provides-Extra: fastapi
Requires-Dist: fastapi>=0.100; extra == 'fastapi'
